README.rst
setup.py
cwl.egg-info/PKG-INFO
cwl.egg-info/SOURCES.txt
cwl.egg-info/dependency_links.txt
cwl.egg-info/top_level.txt
cwlcli/__init__.py